bluesky_adaptive/__init__.py
bluesky_adaptive/_version.py
bluesky_adaptive/on_stop.py
bluesky_adaptive/per_event.py
bluesky_adaptive/per_start.py
bluesky_adaptive/recommendations.py
bluesky_adaptive/scipy_reccomendations.py
bluesky_adaptive/typing.py
bluesky_adaptive/adjudicators/README-ADJUDICATORS.md
bluesky_adaptive/adjudicators/__init__.py
bluesky_adaptive/adjudicators/base.py
bluesky_adaptive/adjudicators/msg.py
bluesky_adaptive/agents/__init__.py
bluesky_adaptive/agents/base.py
bluesky_adaptive/agents/botorch.py
bluesky_adaptive/agents/simple.py
bluesky_adaptive/agents/sklearn.py
bluesky_adaptive/server/__init__.py
bluesky_adaptive/server/comms.py
bluesky_adaptive/server/ioc_server.py
bluesky_adaptive/server/logging_setup.py
bluesky_adaptive/server/server.py
bluesky_adaptive/server/server_api.py
bluesky_adaptive/server/server_resources.py
bluesky_adaptive/server/utils.py
bluesky_adaptive/server/worker.py
bluesky_adaptive/tests/__init__.py
bluesky_adaptive/tests/conftest.py
bluesky_adaptive/tests/test_adjudicators.py
bluesky_adaptive/tests/test_agents.py
bluesky_adaptive/tests/test_botorch_agents.py
bluesky_adaptive/tests/test_communication.py
bluesky_adaptive/tests/test_kafka.py
bluesky_adaptive/tests/test_per_event.py
bluesky_adaptive/tests/test_per_start.py
bluesky_adaptive/tests/test_scipy_rec.py
bluesky_adaptive/tests/test_sklearn_agents.py
bluesky_adaptive/utils/__init__.py
bluesky_adaptive/utils/offline.py
bluesky_adaptive-0.3.2.dist-info/licenses/AUTHORS.rst
bluesky_adaptive-0.3.2.dist-info/licenses/LICENSE
bluesky_adaptive-0.3.2.dist-info/METADATA
bluesky_adaptive-0.3.2.dist-info/WHEEL
bluesky_adaptive-0.3.2.dist-info/top_level.txt
bluesky_adaptive-0.3.2.dist-info/RECORD
