Metadata-Version: 2.4
Name: bluesky-adaptive
Version: 0.3.2
Summary: Tools for writing adaptive plans
Home-page: https://github.com/bluesky/bluesky-adaptive
Author: NSLS-II
Author-email: dama@bnl.gov
License: BSD (3-clause)
Classifier: Development Status :: 2 - Pre-Alpha
Classifier: Natural Language :: English
Classifier: Programming Language :: Python :: 3
Requires-Python: >=3.9
License-File: LICENSE
License-File: AUTHORS.rst
Requires-Dist: bluesky
Requires-Dist: bluesky-live
Requires-Dist: bluesky-widgets
Requires-Dist: bluesky-kafka
Requires-Dist: bluesky-queueserver-api
Requires-Dist: xkcdpass
Requires-Dist: tiled[client]
Requires-Dist: numpy
Requires-Dist: pydantic
Requires-Dist: json-rpc
Provides-Extra: agents
Requires-Dist: scikit-learn; extra == "agents"
Requires-Dist: scipy; extra == "agents"
Requires-Dist: botorch; extra == "agents"
Provides-Extra: dev
Requires-Dist: codecov; extra == "dev"
Requires-Dist: coverage; extra == "dev"
Requires-Dist: flake8; extra == "dev"
Requires-Dist: black; extra == "dev"
Requires-Dist: pytest; extra == "dev"
Requires-Dist: sphinx; extra == "dev"
Requires-Dist: ipython; extra == "dev"
Requires-Dist: matplotlib; extra == "dev"
Requires-Dist: numpydoc; extra == "dev"
Requires-Dist: sphinx-copybutton; extra == "dev"
Requires-Dist: sphinx-design; extra == "dev"
Requires-Dist: pydata-sphinx-theme; extra == "dev"
Requires-Dist: myst-parser; extra == "dev"
Requires-Dist: fastapi; extra == "dev"
Requires-Dist: caproto<1.2.0; extra == "dev"
Requires-Dist: ophyd; extra == "dev"
Requires-Dist: scipy; extra == "dev"
Requires-Dist: pre-commit; extra == "dev"
Requires-Dist: intake; extra == "dev"
Requires-Dist: tiled[server]; extra == "dev"
Requires-Dist: humanize; extra == "dev"
Requires-Dist: doct; extra == "dev"
Requires-Dist: mongomock; extra == "dev"
Requires-Dist: databroker[all]<3.0.0,>=2.0.0b1; extra == "dev"
Requires-Dist: bluesky-tiled-plugins; extra == "dev"
Provides-Extra: all
Requires-Dist: scikit-learn; extra == "all"
Requires-Dist: scipy; extra == "all"
Requires-Dist: botorch; extra == "all"
Requires-Dist: codecov; extra == "all"
Requires-Dist: coverage; extra == "all"
Requires-Dist: flake8; extra == "all"
Requires-Dist: black; extra == "all"
Requires-Dist: pytest; extra == "all"
Requires-Dist: sphinx; extra == "all"
Requires-Dist: ipython; extra == "all"
Requires-Dist: matplotlib; extra == "all"
Requires-Dist: numpydoc; extra == "all"
Requires-Dist: sphinx-copybutton; extra == "all"
Requires-Dist: sphinx-design; extra == "all"
Requires-Dist: pydata-sphinx-theme; extra == "all"
Requires-Dist: myst-parser; extra == "all"
Requires-Dist: fastapi; extra == "all"
Requires-Dist: caproto<1.2.0; extra == "all"
Requires-Dist: ophyd; extra == "all"
Requires-Dist: scipy; extra == "all"
Requires-Dist: pre-commit; extra == "all"
Requires-Dist: intake; extra == "all"
Requires-Dist: tiled[server]; extra == "all"
Requires-Dist: humanize; extra == "all"
Requires-Dist: doct; extra == "all"
Requires-Dist: mongomock; extra == "all"
Requires-Dist: databroker[all]<3.0.0,>=2.0.0b1; extra == "all"
Requires-Dist: bluesky-tiled-plugins; extra == "all"
Dynamic: author
Dynamic: author-email
Dynamic: classifier
Dynamic: description
Dynamic: home-page
Dynamic: license
Dynamic: license-file
Dynamic: provides-extra
Dynamic: requires-dist
Dynamic: requires-python
Dynamic: summary
